backups_rotate/__init__.py
backups_rotate/area.py
backups_rotate/cli.py
backups_rotate/policy.py
backups_rotate-0.0.2.dist-info/METADATA
backups_rotate-0.0.2.dist-info/WHEEL
backups_rotate-0.0.2.dist-info/entry_points.txt
backups_rotate-0.0.2.dist-info/RECORD
