Metadata-Version: 2.3
Name: backups-rotate
Version: 0.0.2
Summary: kind of like logrotate, but for backups
Project-URL: Repository, https://github.com/parmentelat/backups-rotate
Project-URL: Bug Tracker, https://github.com/parmentelat/backups-rotate/issues
Author-email: Thierry Parmentelat <thierry.parmentelat@inria.fr>
License: MIT License
Keywords: backup,database,dump,rotate
Requires-Python: >=3.11
Requires-Dist: click
Requires-Dist: numpy
Requires-Dist: pandas
Requires-Dist: ruamel-yaml
